{
  "test_link": {
    "link": null
  },
  "test_preprocess": {
    "vocab_length": 1804
  },
  "test_build_lm": {
    "english_2_gram_length": 747,
    "english_3_gram_length": 8238,
    "french_3_gram_length": 8285,
    "spanish_3_gram_length": 8468
  },
  "test_eval": {
    "en_on_en": 8.9,
    "en_on_fr": 25.24,
    "en_on_tl": 25.58,
    "en_on_nl": 25.38
  },
  "test_generate": {
    "english_2_gram": "I amoulpeginShmee bie ae",
    "english_3_gram": "I amit: Lynmkm ways.",
    "english_4_gram": "I Love gifts @OndMade a no",
    "spanish_2_gram": "Soycal\u00edodenyegucosie ew",
    "spanish_3_gram": "Soy orbe",
    "french_2_gram": "Je suis:/opapropades tprisl",
    "french_3_gram": "Je suis tune"
  }
}